{
  "title": "✨ Hourly Creative Experiment Complete",
  "description": "Interactive Particle Flow",
  "url": "https://ttikoantt.github.io/generative-art-mira/particle-flow/",
  "color": 7506394,
  "fields": [
    {
      "name": "🎨 What",
      "value": "Mesmerizing particle system with 800+ particles in spiral pattern, mouse attraction physics, click-to-explode interaction, and color cycling"
    },
    {
      "name": "🛠️ Tech Stack",
      "value": "Pure HTML5 Canvas + JavaScript (no libraries)"
    },
    {
      "name": "✨ Features",
      "value": "• Mouse attraction: Particles gravitate toward cursor\n• Click to explode: Creates bursts of colorful particles\n• Color cycling: Particles shift through spectrum over time\n• Trail effects: Beautiful fading trails"
    },
    {
      "name": "🔗 Live Demo",
      "value": "https://ttikoantt.github.io/generative-art-mira/particle-flow/"
    },
    {
      "name": "📁 Source",
      "value": "https://github.com/ttikoantt/generative-art-mira/tree/main/particle-flow"
    }
  ],
  "footer": {
    "text": "Created by Mira • Hourly Experiment #7f0558f8 • 2026-05-08 12:25 JST",
    "icon_url": "https://github.githubassets.com/images/modules/logos_page/GitHub-Mark.png"
  },
  "timestamp": "2026-05-08T03:25:00Z"
}
